cloudbeds_fiscal_document/__init__.py
cloudbeds_fiscal_document/api_client.py
cloudbeds_fiscal_document/api_response.py
cloudbeds_fiscal_document/configuration.py
cloudbeds_fiscal_document/exceptions.py
cloudbeds_fiscal_document/py.typed
cloudbeds_fiscal_document/rest.py
cloudbeds_fiscal_document/api/__init__.py
cloudbeds_fiscal_document/api/configs_api.py
cloudbeds_fiscal_document/api/export_api.py
cloudbeds_fiscal_document/api/features_api.py
cloudbeds_fiscal_document/api/fiscal_documents_api.py
cloudbeds_fiscal_document/models/__init__.py
cloudbeds_fiscal_document/models/action.py
cloudbeds_fiscal_document/models/allocate_receipt_payment_request.py
cloudbeds_fiscal_document/models/allocations_data.py
cloudbeds_fiscal_document/models/allocations_summary.py
cloudbeds_fiscal_document/models/api_error.py
cloudbeds_fiscal_document/models/configs_response.py
cloudbeds_fiscal_document/models/configs_update_request.py
cloudbeds_fiscal_document/models/create_credit_note_request.py
cloudbeds_fiscal_document/models/create_invoice_request.py
cloudbeds_fiscal_document/models/create_receipt_request.py
cloudbeds_fiscal_document/models/create_simple_receipt_request.py
cloudbeds_fiscal_document/models/creation_method.py
cloudbeds_fiscal_document/models/document_action.py
cloudbeds_fiscal_document/models/document_trigger_event.py
cloudbeds_fiscal_document/models/fiscal_document_detailed_response.py
cloudbeds_fiscal_document/models/fiscal_document_email_request.py
cloudbeds_fiscal_document/models/fiscal_document_filters.py
cloudbeds_fiscal_document/models/fiscal_document_kind.py
cloudbeds_fiscal_document/models/fiscal_document_paginated.py
cloudbeds_fiscal_document/models/fiscal_document_patch_request.py
cloudbeds_fiscal_document/models/fiscal_document_recipient.py
cloudbeds_fiscal_document/models/fiscal_document_status.py
cloudbeds_fiscal_document/models/fiscal_document_summary_response.py
cloudbeds_fiscal_document/models/fiscal_document_transaction_allocation.py
cloudbeds_fiscal_document-1.15.0.dist-info/licenses/LICENSE
cloudbeds_fiscal_document-1.15.0.dist-info/METADATA
cloudbeds_fiscal_document-1.15.0.dist-info/WHEEL
cloudbeds_fiscal_document-1.15.0.dist-info/top_level.txt
cloudbeds_fiscal_document-1.15.0.dist-info/RECORD
